rezzie/__init__.py
rezzie/exceptions.py
rezzie/data/seq.fasta
rezzie-1.0.0.dist-info/LICENSE
rezzie-1.0.0.dist-info/METADATA
rezzie-1.0.0.dist-info/WHEEL
rezzie-1.0.0.dist-info/top_level.txt
rezzie-1.0.0.dist-info/RECORD
