Metadata-Version: 2.1
Name: rezzie
Version: 1.0.0
Summary: A small library to access paths to resources shipped with your package.
Author-email: Anders Goncalves da Silva <andersgs@gmail.com>
License: MIT License
Project-URL: homepage, https://github.com/MDU-PHL/rezzie
Project-URL: repository, https://github.com/MDU-PHL/rezzie
Project-URL: documentation, https://github.com/MDU-PHL/rezzie/blob/main/README.md
Project-URL: issues, https://github.com/MDU-PHL/rezzie/issues
Project-URL: changelog, https://github.com/MDU-PHL/rezzie/blob/main/CHANGELOG.md
Keywords: resources,library
Classifier: Programming Language :: Python :: 3
Classifier: Programming Language :: Python :: 3.7
Classifier: Programming Language :: Python :: 3.8
Classifier: Programming Language :: Python :: 3.9
Classifier: Programming Language :: Python :: 3.10
Classifier: Programming Language :: Python :: 3.11
Classifier: License :: OSI Approved :: MIT License
Classifier: Operating System :: OS Independent
Classifier: Topic :: Software Development :: Libraries :: Python Modules
Classifier: Topic :: Scientific/Engineering :: Bio-Informatics
Classifier: Development Status :: 5 - Production/Stable
Requires-Python: <4.0,>=3.7
License-File: LICENSE
Requires-Dist: importlib-resources ; python_version < "3.9"
Provides-Extra: dev
Requires-Dist: black ; extra == 'dev'
Requires-Dist: build ; extra == 'dev'
Requires-Dist: pytest ; extra == 'dev'
Requires-Dist: isort ; extra == 'dev'
Requires-Dist: pylint ; extra == 'dev'
Requires-Dist: twine ; extra == 'dev'
Provides-Extra: test
Requires-Dist: pytest ; extra == 'test'
